TriangleDetective
