Metadata-Version: 2.4
Name: TriangleDetective
Version: 0.1.1
Summary: Triangular Trigonometry
Home-page: 
Author: Abhinav S Nair
Author-email: svnair.1984@gmail.com
License: MIT
Project-URL: Documentation, https://PyTrigPyCharm.readthedocs.io
Project-URL: Source, https://github.com/Sarish002/PyTrigPyCharm
Project-URL: Bug Tracker, https://github.com/Sarish002/PyTrigPyCharm/issues
Keywords: trigonometry
Classifier: Development Status :: 5 - Production/Stable
Classifier: Intended Audience :: Other Audience
Classifier: Operating System :: Microsoft :: Windows :: Windows 11
Classifier: License :: OSI Approved :: MIT License
Classifier: Programming Language :: Python :: 3
License-File: LICENCE.txt
Dynamic: author
Dynamic: author-email
Dynamic: classifier
Dynamic: description
Dynamic: description-content-type
Dynamic: keywords
Dynamic: license
Dynamic: license-file
Dynamic: project-url
Dynamic: summary
